{"id":-431775497,"name_uk":"Калінчук О.І.","name_en":"Kalinchuk O.I.","years":[{"id":2020,"uc":{"gold":0,"silver":2,"bronze":0},"ec":{"gold":0,"silver":0,"bronze":0},"wc":{"gold":0,"silver":0,"bronze":0}},{"id":2018,"uc":{"gold":0,"silver":0,"bronze":1},"ec":{"gold":0,"silver":0,"bronze":0},"wc":{"gold":0,"silver":0,"bronze":1}}],"players":[{"id":14196433,"name_uk":"Слепчук Данило","name_en":"Slepchuk Danylo","uc":{"gold":0,"silver":2,"bronze":1},"ec":{"gold":0,"silver":0,"bronze":0},"wc":{"gold":0,"silver":0,"bronze":1},"rank":1}]}