{"results":[{"rank":1,"type":1,"category":0,"game":1,"gender":1,"id":14111330,"name_uk":"Музичук Анна","name_en":"Muzychuk Anna"},{"rank":1,"type":2,"category":1,"game":1,"gender":0,"id":14122480,"name_uk":"Ветошко Володимир","name_en":"Vetoshko Volodymyr"},{"rank":2,"type":2,"category":4,"game":1,"gender":0,"id":14149494,"name_uk":"Мосесов Даниїл","name_en":"Mosesov Danyil"},{"rank":2,"type":2,"category":4,"game":2,"gender":0,"id":14149494,"name_uk":"Мосесов Даниїл","name_en":"Mosesov Danyil"},{"rank":3,"type":2,"category":1,"game":0,"gender":0,"id":14102250,"name_uk":"Сорока Данило","name_en":"Soroka Danylo"},{"rank":3,"type":2,"category":1,"game":2,"gender":0,"id":14122480,"name_uk":"Ветошко Володимир","name_en":"Vetoshko Volodymyr"},{"rank":3,"type":2,"category":4,"game":0,"gender":0,"id":14137178,"name_uk":"Кириченко Мар'ян","name_en":"Kyrychenko Maryan"},{"rank":3,"type":2,"category":4,"game":1,"gender":0,"id":14137186,"name_uk":"Медведик Володимир","name_en":"Medvedyk Volodymyr"},{"rank":3,"type":2,"category":7,"game":2,"gender":0,"id":14191059,"name_uk":"Карвацький Олексій","name_en":"Karvatskyi Oleksii"},{"rank":4,"type":2,"category":1,"game":2,"gender":0,"id":14122790,"name_uk":"Полуліх Богдан","name_en":"Polulikh Bogdan"},{"rank":4,"type":2,"category":3,"game":2,"gender":1,"id":14153491,"name_uk":"Лєбєдєва Валерія","name_en":"Lebedeva Valeriya"},{"rank":4,"type":2,"category":7,"game":1,"gender":0,"id":14191059,"name_uk":"Карвацький Олексій","name_en":"Karvatskyi Oleksii"},{"rank":5,"type":2,"category":0,"game":0,"gender":0,"id":4152417,"name_uk":"Олексієнко Михайло","name_en":"Oleksiyenko Mykhaylo"},{"rank":5,"type":1,"category":0,"game":0,"gender":1,"id":14114550,"name_uk":"Музичук Марія","name_en":"Muzychuk Mariya"},{"rank":5,"type":2,"category":1,"game":1,"gender":0,"id":14102250,"name_uk":"Сорока Данило","name_en":"Soroka Danylo"},{"rank":5,"type":2,"category":4,"game":0,"gender":0,"id":14149494,"name_uk":"Мосесов Даниїл","name_en":"Mosesov Danyil"},{"rank":5,"type":2,"category":5,"game":2,"gender":0,"id":14174294,"name_uk":"Келеберда Тимур","name_en":"Keleberda Tymur"}]}