{"results":[{"rank":1,"type":2,"category":0,"game":1,"gender":1,"id":14137054,"name_uk":"Бердник Марія","name_en":"Berdnyk Mariia"},{"rank":1,"type":2,"category":0,"game":2,"gender":1,"id":14112035,"name_uk":"Долуханова Євгенія","name_en":"Doluhanova Evgeniya"},{"rank":1,"type":2,"category":4,"game":0,"gender":0,"id":14198525,"name_uk":"Базакуца Святослав","name_en":"Bazakutsa Svyatoslav"},{"rank":1,"type":2,"category":5,"game":1,"gender":1,"id":14191849,"name_uk":"Басова Поліна","name_en":"Basova Polina"},{"rank":2,"type":2,"category":0,"game":1,"gender":0,"id":14100150,"name_uk":"Невєров Валерій","name_en":"Neverov Valeriy"},{"rank":2,"type":2,"category":3,"game":1,"gender":0,"id":14198525,"name_uk":"Базакуца Святослав","name_en":"Bazakutsa Svyatoslav"},{"rank":2,"type":2,"category":4,"game":1,"gender":0,"id":14198525,"name_uk":"Базакуца Святослав","name_en":"Bazakutsa Svyatoslav"},{"rank":2,"type":2,"category":5,"game":2,"gender":0,"id":34160558,"name_uk":"Мариниченко Єгор","name_en":"Marynychenko Yehor"},{"rank":2,"type":2,"category":5,"game":2,"gender":1,"id":14191849,"name_uk":"Басова Поліна","name_en":"Basova Polina"},{"rank":2,"type":2,"category":6,"game":0,"gender":1,"id":34144242,"name_uk":"Добровольська-Рахніна Божен","name_en":"Dobrovolska-Rakhnina Bozhe"},{"rank":3,"type":2,"category":3,"game":0,"gender":0,"id":14198525,"name_uk":"Базакуца Святослав","name_en":"Bazakutsa Svyatoslav"},{"rank":4,"type":2,"category":0,"game":0,"gender":0,"id":14102560,"name_uk":"Моісеєнко Олександр","name_en":"Moiseenko Alexander"},{"rank":4,"type":2,"category":0,"game":0,"gender":1,"id":14137054,"name_uk":"Бердник Марія","name_en":"Berdnyk Mariia"},{"rank":4,"type":2,"category":4,"game":2,"gender":0,"id":14198525,"name_uk":"Базакуца Святослав","name_en":"Bazakutsa Svyatoslav"},{"rank":4,"type":2,"category":4,"game":2,"gender":1,"id":14191849,"name_uk":"Басова Поліна","name_en":"Basova Polina"},{"rank":4,"type":2,"category":6,"game":1,"gender":1,"id":34144242,"name_uk":"Добровольська-Рахніна Божен","name_en":"Dobrovolska-Rakhnina Bozhe"},{"rank":5,"type":2,"category":0,"game":1,"gender":1,"id":14112035,"name_uk":"Долуханова Євгенія","name_en":"Doluhanova Evgeniya"},{"rank":5,"type":2,"category":6,"game":2,"gender":1,"id":34160710,"name_uk":"Репетіло Дар'я","name_en":"Repetilo Daria"}]}