{"id":34127240,"name_uk":"Телюк Анастасія","name_en":"Telyuk Anastasiya","fed":14,"yob":2012,"gender":1,"clubs":[{"id":"1278169672","name_uk":"Городоцька ДЮСШ","name_en":"DYuSSh Horodok"},{"id":"1255997162","name_uk":"Е2-Е4 м.Городок","name_en":"E2–E4 Horodok"}],"coaches":[{"id":"14111055","name_uk":"Мелешко В.М.","name_en":"Meleshko V.M."},{"id":"14112418","name_uk":"Грех А.І.","name_en":"Grekh A.I."}],"results":[{"rank":1,"type":2,"year":2020,"category":7,"game":0,"gender":1},{"rank":1,"type":2,"year":2020,"category":7,"game":1,"gender":1},{"rank":2,"type":2,"year":2025,"category":4,"game":0,"gender":1},{"rank":2,"type":2,"year":2025,"category":4,"game":2,"gender":1},{"rank":2,"type":2,"year":2024,"category":5,"game":1,"gender":1},{"rank":2,"type":2,"year":2023,"category":5,"game":2,"gender":1},{"rank":3,"type":2,"year":2024,"category":5,"game":0,"gender":1},{"rank":3,"type":1,"year":2024,"category":5,"game":2,"gender":1},{"rank":3,"type":2,"year":2020,"category":7,"game":2,"gender":1},{"rank":4,"type":2,"year":2025,"category":4,"game":1,"gender":1},{"rank":4,"type":2,"year":2023,"category":5,"game":0,"gender":1},{"rank":4,"type":2,"year":2024,"category":5,"game":2,"gender":1},{"rank":5,"type":2,"year":2025,"category":1,"game":2,"gender":1},{"rank":5,"type":2,"year":2025,"category":2,"game":2,"gender":1},{"rank":5,"type":2,"year":2026,"category":3,"game":0,"gender":1},{"rank":5,"type":2,"year":2026,"category":3,"game":1,"gender":1}]}