{"id":1114019065,"name_uk":"Black & White","name_en":"Black & White","fed":14,"years":[{"id":2025,"national":{"gold":0,"silver":0,"bronze":0},"international":{"gold":0,"silver":0,"bronze":0}},{"id":2024,"national":{"gold":0,"silver":0,"bronze":0},"international":{"gold":0,"silver":0,"bronze":0}}],"coaches":[{"id":14183765,"name_uk":"Гись Т.Я.","name_en":"Gis T.Ya.","national":{"gold":0,"silver":0,"bronze":0},"international":{"gold":0,"silver":0,"bronze":0},"rank":1}],"players":[{"id":34173587,"name_uk":"Фурда Богдан","name_en":"Furda Bohdan","national":{"gold":0,"silver":0,"bronze":0},"international":{"gold":0,"silver":0,"bronze":0},"rank":1}]}