{"id":1043671362,"name_uk":"ДЮСШ \"Тризуб Плюс\"","name_en":"DYuSSh \"Tryzub Plyus\"","years":[{"id":2023,"national":{"gold":3,"silver":2,"bronze":0},"international":{"gold":0,"silver":0,"bronze":0}},{"id":2022,"national":{"gold":1,"silver":1,"bronze":0},"international":{"gold":0,"silver":0,"bronze":0}},{"id":2021,"national":{"gold":0,"silver":0,"bronze":0},"international":{"gold":0,"silver":0,"bronze":0}},{"id":2019,"national":{"gold":0,"silver":0,"bronze":0},"international":{"gold":0,"silver":0,"bronze":0}}],"coaches":[{"id":14109263,"name_uk":"Губка Р.Б.","name_en":"Gubka R.B.","national":{"gold":4,"silver":3,"bronze":0},"international":{"gold":0,"silver":0,"bronze":0},"rank":1}],"players":[{"id":14184494,"name_uk":"Скарбарчук Тетяна","name_en":"Skarbarchuk Tetyana","national":{"gold":4,"silver":3,"bronze":0},"international":{"gold":0,"silver":0,"bronze":0},"rank":1},{"id":34133933,"name_uk":"Романів Маркіян","name_en":"Romaniv Markiyan","national":{"gold":0,"silver":0,"bronze":0},"international":{"gold":0,"silver":0,"bronze":0},"rank":2}]}