{"results":[{"rank":1,"type":2,"category":7,"game":0,"gender":0,"id":789400,"name_uk":"Кучер Артем","name_en":"Kucher Artem"},{"rank":2,"type":2,"category":1,"game":1,"gender":0,"id":767866,"name_uk":"Щербина Дмитро","name_en":"Scherbina Dmitry"},{"rank":2,"type":2,"category":1,"game":1,"gender":1,"id":767872,"name_uk":"Скакун Катерина","name_en":"Skakun Kateryna"},{"rank":2,"type":2,"category":7,"game":0,"gender":0,"id":789400,"name_uk":"Шабунін Олександр","name_en":"Shabunin Oleksandr"},{"rank":2,"type":2,"category":7,"game":2,"gender":0,"id":789405,"name_uk":"Кучер Артем","name_en":"Kucher Artem"},{"rank":3,"type":1,"category":7,"game":0,"gender":0,"id":793410,"name_uk":"Кучер Артем","name_en":"Kucher Artem"},{"rank":3,"type":2,"category":7,"game":1,"gender":0,"id":789403,"name_uk":"Кучер Артем","name_en":"Kucher Artem"},{"rank":3,"type":2,"category":7,"game":2,"gender":1,"id":789407,"name_uk":"Прокопович Катерина","name_en":"Prokopovych Kateryna"}]}