{"results":[{"rank":1,"id":14104490,"name_uk":"Фірман Н.Б.","name_en":"Firman N.B.","gold":7,"silver":9,"bronze":7},{"rank":2,"id":14107074,"name_uk":"Грабінський В.О.","name_en":"Grabinsky V.O.","gold":6,"silver":7,"bronze":5},{"rank":3,"id":34184880,"name_uk":"","name_en":"","gold":4,"silver":4,"bronze":6},{"rank":4,"id":14116138,"name_uk":"Зазуляк А.А.","name_en":"Zazuliak A.A.","gold":4,"silver":0,"bronze":0},{"rank":5,"id":34125264,"name_uk":"Фарафонов Ю.І.","name_en":"Farafonov Yu.I.","gold":3,"silver":2,"bronze":0},{"rank":6,"id":14113775,"name_uk":"Шевчук О.Є.","name_en":"Shevchuk O.Ye.","gold":3,"silver":1,"bronze":2},{"rank":7,"id":14176203,"name_uk":"Іваницька І.В.","name_en":"Ivanytska I.V.","gold":3,"silver":0,"bronze":0},{"rank":8,"id":14149796,"name_uk":"Макарчук М.А.","name_en":"Makarchuk M.A.","gold":2,"silver":1,"bronze":1},{"rank":8,"id":14136708,"name_uk":"Муха С.В.","name_en":"Mukha S.V.","gold":2,"silver":1,"bronze":1},{"rank":10,"id":14118610,"name_uk":"Вусатюк В.О.","name_en":"Vusatiuk V.O.","gold":2,"silver":0,"bronze":2},{"rank":11,"id":14133040,"name_uk":"Ритенко В.Ю.","name_en":"Rytenko V.Yu.","gold":2,"silver":0,"bronze":0},{"rank":11,"id":14122898,"name_uk":"Шафір М.В.","name_en":"Shafir M.V.","gold":2,"silver":0,"bronze":0},{"rank":13,"id":14104482,"name_uk":"Семенов Д.Г.","name_en":"Semenov D.H.","gold":1,"silver":5,"bronze":1},{"rank":14,"id":14125447,"name_uk":"Чернов Є.А.","name_en":"Chernov Ye.A.","gold":1,"silver":3,"bronze":1},{"rank":15,"id":-1937283595,"name_uk":"Кислинський О.В.","name_en":"Kyslynskyi O.V.","gold":1,"silver":3,"bronze":0},{"rank":16,"id":14106469,"name_uk":"Боднар М.М.","name_en":"Bodnar M.M.","gold":1,"silver":2,"bronze":2},{"rank":17,"id":14159929,"name_uk":"Бутенко О.М.","name_en":"Butenko O.M.","gold":1,"silver":2,"bronze":1},{"rank":18,"id":14114020,"name_uk":"Михайличенко В.А.","name_en":"Mihalichenko V.A.","gold":1,"silver":2,"bronze":0},{"rank":18,"id":34142487,"name_uk":"Чопоров А.В.","name_en":"Choporov A.V.","gold":1,"silver":2,"bronze":0},{"rank":20,"id":-406644032,"name_uk":"Казмірук В.В.","name_en":"Kazmiruk V.V.","gold":1,"silver":1,"bronze":4},{"rank":21,"id":14117509,"name_uk":"Гребенюк С.А.","name_en":"Grebeniuk S.","gold":1,"silver":1,"bronze":2},{"rank":22,"id":-102621827,"name_uk":"Астраханцева О.М.","name_en":"Astrakhantseva O.M.","gold":1,"silver":1,"bronze":0},{"rank":22,"id":14106329,"name_uk":"Кобилянський І.М.","name_en":"Kobylianskyi I.M.","gold":1,"silver":1,"bronze":0},{"rank":22,"id":14128365,"name_uk":"Корнійчук В.В.","name_en":"Kornijchuk V.V.","gold":1,"silver":1,"bronze":0},{"rank":22,"id":14136732,"name_uk":"Роєнко А.О.","name_en":"Roienko A.O.","gold":1,"silver":1,"bronze":0},{"rank":26,"id":14131161,"name_uk":"Григор'єв О.В.","name_en":"Grygoriev O.V.","gold":1,"silver":0,"bronze":3},{"rank":27,"id":14102277,"name_uk":"Гутман Г.М.","name_en":"Gutman H.M.","gold":1,"silver":0,"bronze":1},{"rank":27,"id":14117614,"name_uk":"Куриленко В.А.","name_en":"Kurylenko V.A.","gold":1,"silver":0,"bronze":1},{"rank":29,"id":-1626605272,"name_uk":"Сивук В.О.","name_en":"Syvuk V.O.","gold":1,"silver":0,"bronze":0},{"rank":29,"id":14112434,"name_uk":"Трембач В.","name_en":"Trembach V.","gold":1,"silver":0,"bronze":0},{"rank":31,"id":14117517,"name_uk":"Гриньов В.В.","name_en":"Grinev V.V.","gold":0,"silver":2,"bronze":1},{"rank":32,"id":14111055,"name_uk":"Мелешко В.М.","name_en":"Meleshko V.M.","gold":0,"silver":1,"bronze":3},{"rank":33,"id":34140573,"name_uk":"Мисник Ю.Ю.","name_en":"Mysnyk Yu.Yu.","gold":0,"silver":1,"bronze":1},{"rank":34,"id":-226432678,"name_uk":"Босак В.М.","name_en":"Bosak V.M.","gold":0,"silver":1,"bronze":0},{"rank":34,"id":14105730,"name_uk":"Коробов А.С.","name_en":"Korobov A.S.","gold":0,"silver":1,"bronze":0},{"rank":34,"id":14194287,"name_uk":"Матвієнко М.І.","name_en":"Matviienko M.I.","gold":0,"silver":1,"bronze":0},{"rank":34,"id":14110105,"name_uk":"Тугай С.В.","name_en":"Tugaj S.V.","gold":0,"silver":1,"bronze":0},{"rank":38,"id":13300202,"name_uk":"Каграманянц В.С.","name_en":"Kahramaniants V.S.","gold":0,"silver":0,"bronze":2},{"rank":38,"id":34147659,"name_uk":"Коваль Г.І.","name_en":"Koval H.I.","gold":0,"silver":0,"bronze":2},{"rank":40,"id":14131153,"name_uk":"Гоменюк І.М.","name_en":"Homeniuk I.M.","gold":0,"silver":0,"bronze":1},{"rank":40,"id":14112418,"name_uk":"Грех А.І.","name_en":"Grekh A.I.","gold":0,"silver":0,"bronze":1},{"rank":40,"id":-496799432,"name_uk":"Журба Ю.М.","name_en":"Zhurba Yu.M.","gold":0,"silver":0,"bronze":1},{"rank":40,"id":-264614999,"name_uk":"Ільїн С.О.","name_en":"Ilin S.O.","gold":0,"silver":0,"bronze":1},{"rank":40,"id":14113147,"name_uk":"Кравців М.Р.","name_en":"Kravtsiv M.R.","gold":0,"silver":0,"bronze":1},{"rank":40,"id":14107414,"name_uk":"Кузнецов С.","name_en":"Kusnetsov S.","gold":0,"silver":0,"bronze":1},{"rank":40,"id":14131684,"name_uk":"Мацейко М.Р.","name_en":"Matseyko M.R.","gold":0,"silver":0,"bronze":1},{"rank":40,"id":14109964,"name_uk":"Плостак Г.Я.","name_en":"Plostak H.Ya.","gold":0,"silver":0,"bronze":1},{"rank":40,"id":34190430,"name_uk":"Слободянюк Я.В.","name_en":"Slobodyanyk Ya.V.","gold":0,"silver":0,"bronze":1},{"rank":40,"id":14165040,"name_uk":"Цираковський С.В.","name_en":"Tsirakovsky S.V.","gold":0,"silver":0,"bronze":1}]}