{"results":[{"rank":4,"type":2,"year":2019,"category":5,"game":0,"gender":0,"id":14156024,"name_uk":"Сідлецький Іван","name_en":"Sidletskyi Ivan"},{"rank":4,"type":2,"year":2015,"category":7,"game":0,"gender":0,"id":14156024,"name_uk":"Сідлецький Іван","name_en":"Sidletskyi Ivan"},{"rank":4,"type":2,"year":2014,"category":7,"game":1,"gender":0,"id":14156024,"name_uk":"Сідлецький Іван","name_en":"Sidletskyi Ivan"},{"rank":5,"type":2,"year":2017,"category":6,"game":0,"gender":0,"id":14156024,"name_uk":"Сідлецький Іван","name_en":"Sidletskyi Ivan"}]}