[{"id":1121078,"type":2,"location_uk":"м.Львів","location_en":"Lviv","date":"13.03-19.03","round":9,"rounds":9,"results":[{"rank":1,"id":34183973,"name_uk":"Кравчук Дар'я","name_en":"Kravchuk Daria","fed":11,"notes":"Буча Ківі  Корнійчук В.В., Кобилянс"},{"rank":2,"id":91138744,"name_uk":"Печенізька-Ткачова Олеся","name_en":"Pechenizka-Tkachova Olesia","fed":21,"notes":"КДЮСШ-4  Кубата В.В."},{"rank":3,"id":34190732,"name_uk":"Кочерга Єлізавєта","name_en":"Kocherha Yelizavieta","fed":1,"notes":"Шахова школа  Семенов Д.Г., Бабіч Ф"},{"rank":4,"id":34185771,"name_uk":"Борутя Анастасія","name_en":"Borutia Anastasiia","fed":11,"notes":"ДЮСШ \"Юність\"  Кириченко В.М., Мела"},{"rank":5,"id":-1373278385,"name_uk":"Бурак-Потоцька Софія","name_en":"Бурак-Потоцька Софія","fed":1,"notes":"Ківі  Корнійчук В.В."}]}]