[{"id":562238,"type":2,"location_uk":"м.Одеса","location_en":"Odesa","date":"14.06","round":9,"rounds":9,"results":[{"rank":1,"id":34166300,"name_uk":"Шнейдер Ілля","name_en":"Shneider Illia","fed":1,"points":7.5},{"rank":2,"id":34151893,"name_uk":"Перепелиця Юрій","name_en":"Perepelytsia Yuriy","fed":3,"points":7.5},{"rank":3,"id":34129227,"name_uk":"Криштафор Максим","name_en":"Kryshtafor Maksym","fed":16,"points":7.0},{"rank":4,"id":34160523,"name_uk":"Кіпень Святослав","name_en":"Kipen Svyatoslav","fed":14,"points":7.0},{"rank":5,"id":34162909,"name_uk":"Шуляков Олег","name_en":"Shulyakov Oleg","fed":9,"points":7.0}]}]