[{"id":764516,"type":2,"location_uk":"м.Полтава","location_en":"Poltava","date":"24.05-29.05","round":9,"rounds":9,"results":[{"rank":1,"id":34169342,"name_uk":"Дьомін Ян","name_en":"Domin Yan","fed":1},{"rank":2,"id":34121307,"name_uk":"Артемов Андрій","name_en":"Artemov Andriy","fed":11},{"rank":3,"id":34139931,"name_uk":"Пільчук Артем","name_en":"Pilchuk Artem","fed":11},{"rank":4,"id":34144684,"name_uk":"Шевченко Ярослав","name_en":"Shevchenko Yaroslav","fed":23},{"rank":5,"id":34159231,"name_uk":"Бабаєв Мурад","name_en":"Babayev Murad","fed":17}]}]