[{"rank":1,"name":"Штембуляк Євген","fide":"","fed":"ОДЕ","notes":"","club":"","coach1":"","coach2":""},{"rank":2,"name":"Мірзоєв Еміль","fide":"","fed":"ОДЕ","notes":"","club":"","coach1":"","coach2":""},{"rank":3,"name":"Полуліх Богдан","fide":"","fed":"ЛЬВ","notes":"","club":"","coach1":"","coach2":""},{"rank":4,"name":"Крикун Юрій","fide":"","fed":"КИЇ","notes":"","club":"","coach1":"","coach2":""},{"rank":5,"name":"Пен Лі","fide":"","fed":"МИК","notes":"","club":"","coach1":"","coach2":""}]