[{"rank":1,"name":"Величко Семен","fide":"","fed":"ЛЬВ","notes":"ДЮСШ Дебют  Грабінський В.О.","club":"","coach1":"","coach2":""},{"rank":2,"name":"Матієвський Ростислав","fide":"","fed":"І-Ф","notes":"ДЮСШ № 3  Кобилянський І.М.","club":"","coach1":"","coach2":""},{"rank":3,"name":"Кіпень Святослав","fide":"","fed":"ЛЬВ","notes":"ДЮСШ Дебют  Грабінський В.О.","club":"","coach1":"","coach2":""},{"rank":4,"name":"Павлик Максим","fide":"","fed":"ЛЬВ","notes":"ЛША  Фірман Н.Б.","club":"","coach1":"","coach2":""},{"rank":5,"name":"Молчанов Роман","fide":"","fed":"ЛЬВ","notes":"ЛША  Фірман Н.Б., Мацейко М.Р.","club":"","coach1":"","coach2":""}]