[{"rank":1,"name":"Мартинкова Олена","fide":"","fed":"ДОН","notes":"","club":"","coach1":"","coach2":""},{"rank":2,"name":"Бердник Марія","fide":"","fed":"ХАР","notes":"","club":"","coach1":"","coach2":""},{"rank":3,"name":"Грищенко Каміла","fide":"","fed":"ДОН","notes":"","club":"","coach1":"","coach2":""},{"rank":4,"name":"Козаченко Софія","fide":"","fed":"ДОН","notes":"","club":"","coach1":"","coach2":""},{"rank":5,"name":"Малануха Маргарита","fide":"","fed":"ЗАП","notes":"","club":"","coach1":"","coach2":""}]