[{"rank":1,"name":"Трушко Андрій","fide":"","fed":"КИЇ","notes":"","club":"","coach1":"","coach2":""},{"rank":2,"name":"Дегтярьов Роман","fide":"","fed":"ХАР","notes":"","club":"","coach1":"","coach2":""},{"rank":3,"name":"Лозинський Богдан","fide":"","fed":"І-Ф","notes":"","club":"","coach1":"","coach2":""},{"rank":4,"name":"Прокоф'єв Валентин","fide":"","fed":"І-Ф","notes":"","club":"","coach1":"","coach2":""},{"rank":5,"name":"Дубневич Максим","fide":"","fed":"ЛЬВ","notes":"","club":"","coach1":"","coach2":""}]