[{"rank":1,"name":"Коробов Антон","fide":"","fed":"ХАР","notes":"","club":"","coach1":"","coach2":""},{"rank":2,"name":"Шевченко Кірілл","fide":"","fed":"КИЇ","notes":"","club":"","coach1":"","coach2":""},{"rank":3,"name":"Кузубов Юрій","fide":"","fed":"ДОН","notes":"","club":"","coach1":"","coach2":""},{"rank":4,"name":"Зубов Олександр","fide":"","fed":"МИК","notes":"","club":"","coach1":"","coach2":""},{"rank":5,"name":"Бернадський Віталій","fide":"","fed":"ЧНО","notes":"","club":"","coach1":"","coach2":""}]