[{"id":1305306,"type":2,"location_uk":"Lviv, V. Chornovola st, 7","location_en":"Lviv, V. Chornovola st, 7","date":"15.12-22.12","round":5,"rounds":9,"results":[{"rank":1,"id":14186640,"name_uk":"Дегтярьов Роман","name_en":"Dehtiarov Roman","fed":21,"points":4.5},{"rank":2,"id":14124890,"name_uk":"Бахмацький Владислав","name_en":"Bakhmatsky Vladislav","fed":13,"points":4.5},{"rank":3,"id":14189828,"name_uk":"Лях Василь","name_en":"Lyakh Vasiliy","fed":5,"points":4.5},{"rank":4,"id":14191059,"name_uk":"Карвацький Олексій","name_en":"Karvatskyi Oleksii","fed":14,"points":4.5},{"rank":5,"id":34161627,"name_uk":"Масняк Юрій","name_en":"Masnyak Yuriy","fed":14,"points":4.0}]}]