[{"id":167017,"type":2,"location_uk":"м.Миколаїв","location_en":"Mykolaiv","date":"25.03-02.04","round":11,"rounds":11,"results":[{"rank":1,"id":14137054,"name_uk":"Бердник Марія","name_en":"Berdnyk Mariia","fed":21,"points":9.5},{"rank":2,"id":14172909,"name_uk":"Руккас Олена","name_en":"Rukkas Elena","fed":21,"points":7.0},{"rank":3,"id":14159112,"name_uk":"Константінова Вікторія","name_en":"Konstantinova Viktoriia","fed":16,"points":7.0},{"rank":4,"id":14155915,"name_uk":"Романюк Лідія","name_en":"Romanyuk Lidiya","fed":20,"points":6.5},{"rank":5,"id":14137097,"name_uk":"Відрук Марія","name_en":"Vidruk Mariia","fed":16,"points":6.5}]}]