[{"id":459971,"type":1,"location_uk":"Bratislava, Incheba Expo","location_en":"Bratislava, Incheba Expo","date":"02.08-10.08","round":9,"rounds":9,"results":[{"rank":4,"id":14165210,"name_uk":"Петровський Вадим","fed":8,"coach1":{"id":"14137224","name_uk":"Вачиля А.","name_en":"Vachylia A."},"notes":"Вачиля А. (Мукачево)","points":7.0}]},{"id":427241,"type":2,"location_uk":"с.Давидів","location_en":"Davydiv","date":"19.03-29.03","round":11,"rounds":11,"results":[{"rank":1,"id":14165210,"name_uk":"Петровський Вадим","fed":8,"club":{"id":"1004523081","name_uk":"ДЮШаК м.Мукачево","name_en":"DYuShaK Mukachevo"},"coach1":{"id":"14135744","name_uk":"Кейк М.М.","name_en":"Keik M.M."},"notes":"ДЮШаК Мукачево (Кейк М.М.)","points":9.0},{"rank":2,"id":14198525,"name_uk":"Базакуца Святослав","name_en":"Bazakutsa Svyatoslav","fed":21,"points":7.5},{"rank":3,"id":14187086,"name_uk":"Самуненков Ігор","name_en":"Samunenkov Ihor","fed":1,"club":{"id":"1773301036","name_uk":"Шахова школа","name_en":"Shakhova Shkola"},"coach1":{"id":"14104482","name_uk":"Семенов Д.Г.","name_en":"Semenov D.H."},"notes":"Шахова Школа / Семенов Д.Г.","points":7.5},{"rank":4,"id":14156024,"name_uk":"Сідлецький Іван","name_en":"Sidletskyi Ivan","fed":1,"points":7.5},{"rank":5,"id":14187914,"name_uk":"Подольський Михайло","name_en":"Podolskyi Mykhailo","fed":1,"club":{"id":"1234937561","name_uk":"ШЦ \"Товариш\"","name_en":"Tovarysh"},"coach1":{"id":"14101467","name_uk":"Рахмангулов А.З.","name_en":"Rakhmangulov A.Z."},"notes":"ШЦ \"Товариш\" / Рахмангулов А.З.","points":6.5}]}]