[{"id":1230646,"type":1,"location_uk":"Porto Palace Hotel, Thessaloniki, Greece","location_en":"Porto Palace Hotel, Thessaloniki, Greece","date":"07.08","round":7,"rounds":18,"results":[{"rank":2,"id":529014778,"name_uk":"Брюхович Кароліна","name_en":"Briukhovych Karolina","fed":11,"points":5.0}]},{"id":1183887,"type":2,"location_uk":"с.Світязь, Шацьк","location_en":"Shatsk","date":"01.06","round":11,"rounds":11,"results":[{"rank":1,"id":34185828,"name_uk":"Попова Анна","name_en":"Popova Anna","fed":14,"club":"Городоцька ДЮСШ","coach1":"Грех А.І.","coach2":"Мелешко В.М.","notes":"Городоцька ДЮСШ Грех А., Мелешко В.М. ","points":8.5},{"rank":2,"id":529008573,"name_uk":"Кривуцька Марта","name_en":"Kryvutska Marta","fed":10,"club":"Кімната школяра","coach1":"Шевчук Г.В.","coach2":"Оленчук С.Р.","notes":"Кімната Школяра Шевчук Г.В., Оленчук С.Р.","points":8.0},{"rank":3,"id":529008930,"name_uk":"Левченко Іванна","name_en":"Levchenko Ivanna","fed":1,"club":"Funzone Chess Club","coach1":"Никоненко М.Ю.","notes":"Funzone Chess Club Никоненко М.Ю.","points":7.5},{"rank":4,"id":529014778,"name_uk":"Брюхович Кароліна","name_en":"Briukhovych Karolina","fed":11,"club":"Броварська ДЮСШ","coach1":"Гребенюк С.А.","notes":"Гребенюк С.А.","points":7.5},{"rank":5,"id":529009561,"name_uk":"Трет'якова Каріна","name_en":"Tretiakova Karina","fed":5,"club":"ДЮСШ №3","coach1":"Казмірук В.В.","notes":"ДЮСШ №3 Казмірук В.В.","points":7.5}]}]