{"president_uk":"Мороховський В.В.","president_en":"Morokhovskyi V.V.","site":"chessclub.com.ua","facebook":"facebook.com/groups/1854696784841456","years":[{"id":2024,"uc":{"gold":0,"silver":0,"bronze":0},"ec":{"gold":1,"silver":1,"bronze":0},"wc":{"gold":0,"silver":0,"bronze":0}},{"id":2023,"uc":{"gold":2,"silver":1,"bronze":2},"ec":{"gold":0,"silver":0,"bronze":0},"wc":{"gold":0,"silver":0,"bronze":0}},{"id":2022,"uc":{"gold":2,"silver":0,"bronze":0},"ec":{"gold":0,"silver":0,"bronze":1},"wc":{"gold":1,"silver":0,"bronze":4}},{"id":2021,"uc":{"gold":4,"silver":5,"bronze":3},"ec":{"gold":0,"silver":0,"bronze":0},"wc":{"gold":0,"silver":0,"bronze":0}},{"id":2020,"uc":{"gold":3,"silver":6,"bronze":4},"ec":{"gold":0,"silver":0,"bronze":0},"wc":{"gold":0,"silver":0,"bronze":0}},{"id":2019,"uc":{"gold":5,"silver":5,"bronze":8},"ec":{"gold":0,"silver":0,"bronze":1},"wc":{"gold":1,"silver":0,"bronze":0}},{"id":2018,"uc":{"gold":4,"silver":4,"bronze":5},"ec":{"gold":0,"silver":0,"bronze":0},"wc":{"gold":0,"silver":0,"bronze":0}},{"id":2017,"uc":{"gold":4,"silver":2,"bronze":6},"ec":{"gold":0,"silver":0,"bronze":0},"wc":{"gold":0,"silver":0,"bronze":0}},{"id":2016,"uc":{"gold":4,"silver":10,"bronze":3},"ec":{"gold":0,"silver":0,"bronze":0},"wc":{"gold":0,"silver":0,"bronze":0}},{"id":2015,"uc":{"gold":7,"silver":7,"bronze":9},"ec":{"gold":1,"silver":0,"bronze":0},"wc":{"gold":0,"silver":0,"bronze":0}},{"id":2014,"uc":{"gold":3,"silver":5,"bronze":4},"ec":{"gold":0,"silver":0,"bronze":0},"wc":{"gold":0,"silver":0,"bronze":0}}],"clubs":[{"id":1217532066,"name_uk":"Чорноморська ДЮСШ","name_en":"DYuSSh Chornomorsk","uc":{"gold":2,"silver":0,"bronze":0},"ec":{"gold":0,"silver":0,"bronze":1},"wc":{"gold":1,"silver":0,"bronze":1},"rank":1},{"id":1320444012,"name_uk":"КДЮСШ м.Одеса","name_en":"KDYuSSh Odesa","uc":{"gold":1,"silver":1,"bronze":1},"ec":{"gold":0,"silver":0,"bronze":0},"wc":{"gold":0,"silver":0,"bronze":2},"rank":2},{"id":1916950855,"name_uk":"ЛША","name_en":"LShA","uc":{"gold":0,"silver":0,"bronze":1},"ec":{"gold":0,"silver":1,"bronze":0},"wc":{"gold":0,"silver":0,"bronze":0},"rank":3},{"id":1773301036,"name_uk":"Шахова школа","name_en":"Shakhova Shkola","uc":{"gold":0,"silver":1,"bronze":0},"ec":{"gold":0,"silver":0,"bronze":0},"wc":{"gold":0,"silver":0,"bronze":0},"rank":4},{"id":1152719131,"name_uk":"ДЮСШШШ м.Одеса","name_en":"DYuSSh Odesa","uc":{"gold":0,"silver":0,"bronze":0},"ec":{"gold":0,"silver":0,"bronze":0},"wc":{"gold":0,"silver":0,"bronze":1},"rank":5},{"id":1436662520,"name_uk":"Сарата-ШАХ","name_en":"Sarata-Shakh","uc":{"gold":0,"silver":0,"bronze":0},"ec":{"gold":0,"silver":0,"bronze":0},"wc":{"gold":0,"silver":0,"bronze":0},"rank":5}],"coaches":[{"id":14114127,"name_uk":"Білий В.Б.","name_en":"Biliy V.B.","uc":{"gold":6,"silver":1,"bronze":1},"ec":{"gold":0,"silver":0,"bronze":2},"wc":{"gold":1,"silver":0,"bronze":1},"rank":1},{"id":14100304,"name_uk":"Богданов В.","name_en":"Bogdanov V.","uc":{"gold":2,"silver":3,"bronze":3},"ec":{"gold":0,"silver":0,"bronze":0},"wc":{"gold":0,"silver":0,"bronze":2},"rank":2},{"id":14113635,"name_uk":"Горбунов І.Н.","name_en":"Gorbunov I.N.","uc":{"gold":1,"silver":1,"bronze":0},"ec":{"gold":0,"silver":0,"bronze":0},"wc":{"gold":0,"silver":0,"bronze":0},"rank":3},{"id":14118610,"name_uk":"Вусатюк В.О.","name_en":"Vusatiuk V.O.","uc":{"gold":0,"silver":1,"bronze":2},"ec":{"gold":0,"silver":0,"bronze":0},"wc":{"gold":0,"silver":0,"bronze":0},"rank":4},{"id":14102137,"name_uk":"Тисевич Р.","name_en":"Tisevich R.","uc":{"gold":0,"silver":1,"bronze":2},"ec":{"gold":0,"silver":0,"bronze":0},"wc":{"gold":0,"silver":0,"bronze":0},"rank":4},{"id":14163977,"name_uk":"Мовчан В.","name_en":"Movchan V.","uc":{"gold":0,"silver":1,"bronze":1},"ec":{"gold":0,"silver":0,"bronze":0},"wc":{"gold":0,"silver":0,"bronze":0},"rank":6},{"id":14104490,"name_uk":"Фірман Н.Б.","name_en":"Firman N.B.","uc":{"gold":0,"silver":0,"bronze":1},"ec":{"gold":0,"silver":1,"bronze":0},"wc":{"gold":0,"silver":0,"bronze":0},"rank":6},{"id":34118691,"name_uk":"Горошкова І.","name_en":"Goroshkova I.","uc":{"gold":0,"silver":1,"bronze":0},"ec":{"gold":0,"silver":0,"bronze":0},"wc":{"gold":0,"silver":0,"bronze":1},"rank":8},{"id":14117479,"name_uk":"Рахмангулова А.","name_en":"Rakhmangulova A.","uc":{"gold":0,"silver":0,"bronze":0},"ec":{"gold":0,"silver":1,"bronze":0},"wc":{"gold":0,"silver":0,"bronze":0},"rank":8},{"id":14104482,"name_uk":"Семенов Д.Г.","name_en":"Semenov D.H.","uc":{"gold":0,"silver":1,"bronze":0},"ec":{"gold":0,"silver":0,"bronze":0},"wc":{"gold":0,"silver":0,"bronze":0},"rank":8},{"id":-1580452929,"name_uk":"Морозова","name_en":"Morozova","uc":{"gold":0,"silver":0,"bronze":1},"ec":{"gold":0,"silver":0,"bronze":0},"wc":{"gold":0,"silver":0,"bronze":0},"rank":11},{"id":-1054714848,"name_uk":"Тісевич Р.","name_en":"Tisevych R.","uc":{"gold":0,"silver":0,"bronze":1},"ec":{"gold":0,"silver":0,"bronze":0},"wc":{"gold":0,"silver":0,"bronze":0},"rank":11},{"id":-62493978,"name_uk":"Лев А.Я.","name_en":"Lev A.Ya.","uc":{"gold":0,"silver":0,"bronze":0},"ec":{"gold":0,"silver":0,"bronze":0},"wc":{"gold":0,"silver":0,"bronze":0},"rank":13},{"id":14109301,"name_uk":"Фінгеров Д.","name_en":"Fingerov D.","uc":{"gold":0,"silver":0,"bronze":0},"ec":{"gold":0,"silver":0,"bronze":0},"wc":{"gold":0,"silver":0,"bronze":0},"rank":13}],"players":[{"id":14174669,"name_uk":"Гризлова Софія","name_en":"Hryzlova Sofiia","uc":{"gold":6,"silver":4,"bronze":4},"ec":{"gold":0,"silver":0,"bronze":2},"wc":{"gold":1,"silver":0,"bronze":1},"rank":1},{"id":14113325,"name_uk":"Штембуляк Євген","name_en":"Shtembuliak Evgeny","uc":{"gold":6,"silver":2,"bronze":0},"ec":{"gold":0,"silver":0,"bronze":0},"wc":{"gold":1,"silver":0,"bronze":0},"rank":2},{"id":14138611,"name_uk":"Мац Діана","name_en":"Mats Diana","uc":{"gold":5,"silver":7,"bronze":3},"ec":{"gold":0,"silver":0,"bronze":0},"wc":{"gold":0,"silver":0,"bronze":0},"rank":3},{"id":14165570,"name_uk":"Тобак Михайло","name_en":"Tobak Mikhail","uc":{"gold":5,"silver":3,"bronze":5},"ec":{"gold":0,"silver":0,"bronze":0},"wc":{"gold":0,"silver":0,"bronze":2},"rank":4},{"id":14115298,"name_uk":"Богданович Станіслав","name_en":"Bogdanovich Stanislav","uc":{"gold":3,"silver":3,"bronze":3},"ec":{"gold":0,"silver":0,"bronze":0},"wc":{"gold":0,"silver":0,"bronze":0},"rank":5},{"id":14142317,"name_uk":"Байдецький Валентин","uc":{"gold":2,"silver":1,"bronze":5},"ec":{"gold":0,"silver":0,"bronze":0},"wc":{"gold":0,"silver":0,"bronze":0},"rank":6},{"id":14101513,"name_uk":"Жукова Наталія","name_en":"Zhukova Natalia","uc":{"gold":1,"silver":1,"bronze":1},"ec":{"gold":1,"silver":0,"bronze":0},"wc":{"gold":0,"silver":0,"bronze":0},"rank":7},{"id":14140110,"name_uk":"Шумейко Ганна","name_en":"Shumeyko Anna","uc":{"gold":2,"silver":0,"bronze":1},"ec":{"gold":0,"silver":0,"bronze":0},"wc":{"gold":0,"silver":0,"bronze":0},"rank":8},{"id":14134020,"name_uk":"Юровських Олександр","name_en":"Yurovskykh Oleksandr","uc":{"gold":1,"silver":2,"bronze":2},"ec":{"gold":0,"silver":0,"bronze":0},"wc":{"gold":0,"silver":0,"bronze":0},"rank":9},{"id":14162180,"name_uk":"Лимар Владислав","name_en":"Lymar Vladislav","uc":{"gold":1,"silver":1,"bronze":3},"ec":{"gold":0,"silver":0,"bronze":0},"wc":{"gold":0,"silver":0,"bronze":0},"rank":10},{"id":14142805,"name_uk":"Домальчук-Йонассон Олександр","name_en":"Domalchuk-Jonasson Aleksandr","uc":{"gold":1,"silver":1,"bronze":2},"ec":{"gold":0,"silver":0,"bronze":0},"wc":{"gold":0,"silver":0,"bronze":0},"rank":11},{"id":14148714,"name_uk":"Баруді Даніїл","name_en":"Barudi Daniil","uc":{"gold":1,"silver":1,"bronze":1},"ec":{"gold":0,"silver":0,"bronze":0},"wc":{"gold":0,"silver":0,"bronze":0},"rank":12},{"id":14142716,"name_uk":"Горошков Максим","name_en":"Goroshkov Maksym","uc":{"gold":1,"silver":1,"bronze":1},"ec":{"gold":0,"silver":0,"bronze":0},"wc":{"gold":0,"silver":0,"bronze":1},"rank":12},{"id":14190427,"name_uk":"Ковальова Таїсія","name_en":"Kovalyova Taisiya","uc":{"gold":1,"silver":1,"bronze":0},"ec":{"gold":0,"silver":0,"bronze":0},"wc":{"gold":0,"silver":0,"bronze":0},"rank":14},{"id":14153084,"name_uk":"Кукелко Олексій","name_en":"Kukelko Alexey","uc":{"gold":1,"silver":0,"bronze":2},"ec":{"gold":0,"silver":0,"bronze":0},"wc":{"gold":0,"silver":0,"bronze":0},"rank":15},{"id":14172992,"name_uk":"Муханова Єлизавета","name_en":"Mukhanova Elizaveta","uc":{"gold":1,"silver":0,"bronze":0},"ec":{"gold":0,"silver":0,"bronze":0},"wc":{"gold":0,"silver":0,"bronze":0},"rank":16},{"id":34144838,"name_uk":"Руссєва Світлана","name_en":"Russieva Svitlana","uc":{"gold":0,"silver":0,"bronze":0},"ec":{"gold":1,"silver":0,"bronze":0},"wc":{"gold":0,"silver":0,"bronze":0},"rank":16},{"id":14108640,"name_uk":"Мирзоев Эмиль","name_en":"Mirzoev Emil","uc":{"gold":0,"silver":4,"bronze":1},"ec":{"gold":0,"silver":0,"bronze":0},"wc":{"gold":0,"silver":0,"bronze":0},"rank":18},{"id":14162202,"name_uk":"Волощук Ілля","name_en":"Voloshchuk Iliya","uc":{"gold":0,"silver":2,"bronze":2},"ec":{"gold":0,"silver":0,"bronze":0},"wc":{"gold":0,"silver":0,"bronze":0},"rank":19},{"id":14188392,"name_uk":"Чехані Анна","name_en":"Chekhani Anna","uc":{"gold":0,"silver":2,"bronze":0},"ec":{"gold":0,"silver":0,"bronze":0},"wc":{"gold":0,"silver":0,"bronze":0},"rank":20},{"id":34116389,"name_uk":"Безейко Олександр","name_en":"Bezeyko Olexander","uc":{"gold":0,"silver":1,"bronze":1},"ec":{"gold":0,"silver":0,"bronze":0},"wc":{"gold":0,"silver":0,"bronze":0},"rank":21},{"id":14137097,"name_uk":"Відрук Марія","name_en":"Vidruk Mariia","uc":{"gold":0,"silver":1,"bronze":1},"ec":{"gold":0,"silver":0,"bronze":0},"wc":{"gold":0,"silver":0,"bronze":0},"rank":21},{"id":14159112,"name_uk":"Константінова Вікторія","name_en":"Konstantinova Viktoriia","uc":{"gold":0,"silver":1,"bronze":1},"ec":{"gold":0,"silver":0,"bronze":0},"wc":{"gold":0,"silver":0,"bronze":0},"rank":21},{"id":34129227,"name_uk":"Криштафор Максим","name_en":"Kryshtafor Maksym","uc":{"gold":0,"silver":0,"bronze":1},"ec":{"gold":0,"silver":1,"bronze":0},"wc":{"gold":0,"silver":0,"bronze":0},"rank":21},{"id":34116141,"name_uk":"Мовчан Наталія","name_en":"Movchan Nataliya","uc":{"gold":0,"silver":1,"bronze":1},"ec":{"gold":0,"silver":0,"bronze":0},"wc":{"gold":0,"silver":0,"bronze":0},"rank":21},{"id":14151570,"name_uk":"Руссєва Вікторія","name_en":"Russeva Viktoria","uc":{"gold":0,"silver":1,"bronze":1},"ec":{"gold":0,"silver":0,"bronze":0},"wc":{"gold":0,"silver":0,"bronze":0},"rank":21},{"id":14138158,"name_uk":"Дідик Діана","name_en":"Didyk Diana","uc":{"gold":0,"silver":1,"bronze":0},"ec":{"gold":0,"silver":0,"bronze":0},"wc":{"gold":0,"silver":0,"bronze":0},"rank":27},{"id":34132902,"name_uk":"Саакян Арам","name_en":"Sahakyan Aram A","uc":{"gold":0,"silver":1,"bronze":0},"ec":{"gold":0,"silver":0,"bronze":0},"wc":{"gold":0,"silver":0,"bronze":0},"rank":27},{"id":34336060,"name_uk":"Семенова Василина","name_en":"Semenova Vasylyna","uc":{"gold":0,"silver":1,"bronze":0},"ec":{"gold":0,"silver":0,"bronze":0},"wc":{"gold":0,"silver":0,"bronze":0},"rank":27},{"id":14157713,"name_uk":"Тарасенко Владислав","name_en":"Tarasenko Vladislav","uc":{"gold":0,"silver":1,"bronze":0},"ec":{"gold":0,"silver":0,"bronze":0},"wc":{"gold":0,"silver":0,"bronze":0},"rank":27},{"id":34107428,"name_uk":"Бабаян Баграт","name_en":"Babaian Bagrat","uc":{"gold":0,"silver":0,"bronze":2},"ec":{"gold":0,"silver":0,"bronze":0},"wc":{"gold":0,"silver":0,"bronze":0},"rank":31},{"id":14137119,"name_uk":"Аникєєв Артем","name_en":"Anikieiev Artem","uc":{"gold":0,"silver":0,"bronze":0},"ec":{"gold":0,"silver":0,"bronze":0},"wc":{"gold":0,"silver":0,"bronze":0},"rank":32},{"id":14113406,"name_uk":"Борсук Костянтин","name_en":"Borsuk Konstantin","uc":{"gold":0,"silver":0,"bronze":0},"ec":{"gold":0,"silver":0,"bronze":0},"wc":{"gold":0,"silver":0,"bronze":0},"rank":32},{"id":14167131,"name_uk":"Вернигора Олександра","name_en":"Vernigora Alexandra","uc":{"gold":0,"silver":0,"bronze":0},"ec":{"gold":0,"silver":0,"bronze":0},"wc":{"gold":0,"silver":0,"bronze":0},"rank":32},{"id":34100270,"name_uk":"Гарський Владислав","name_en":"Garsky Vladyslav","uc":{"gold":0,"silver":0,"bronze":0},"ec":{"gold":0,"silver":0,"bronze":0},"wc":{"gold":0,"silver":0,"bronze":0},"rank":32},{"id":34106138,"name_uk":"Завезіон Ніка","name_en":"Zavezion Nika","uc":{"gold":0,"silver":0,"bronze":0},"ec":{"gold":0,"silver":0,"bronze":0},"wc":{"gold":0,"silver":0,"bronze":0},"rank":32},{"id":14157675,"name_uk":"Камнев Олександр","name_en":"Kamnev Alexandr","uc":{"gold":0,"silver":0,"bronze":0},"ec":{"gold":0,"silver":0,"bronze":0},"wc":{"gold":0,"silver":0,"bronze":0},"rank":32},{"id":14104059,"name_uk":"Ковальов Денис","name_en":"Kovalev Denis","uc":{"gold":0,"silver":0,"bronze":0},"ec":{"gold":0,"silver":0,"bronze":0},"wc":{"gold":0,"silver":0,"bronze":0},"rank":32},{"id":34122729,"name_uk":"Пономаренко Тимофій","name_en":"Ponomarenko Tymofiy","uc":{"gold":0,"silver":0,"bronze":0},"ec":{"gold":0,"silver":0,"bronze":0},"wc":{"gold":0,"silver":0,"bronze":0},"rank":32},{"id":-1014363150,"name_uk":"Савченко Арiна","name_en":"Savchenko Arina","uc":{"gold":0,"silver":0,"bronze":0},"ec":{"gold":0,"silver":0,"bronze":0},"wc":{"gold":0,"silver":0,"bronze":0},"rank":32},{"id":14143488,"name_uk":"Снігуров Максим","name_en":"Snigurov Maxim","uc":{"gold":0,"silver":0,"bronze":0},"ec":{"gold":0,"silver":0,"bronze":0},"wc":{"gold":0,"silver":0,"bronze":0},"rank":32},{"id":34107754,"name_uk":"Терлецька Марія","name_en":"Terletska Mariia","uc":{"gold":0,"silver":0,"bronze":0},"ec":{"gold":0,"silver":0,"bronze":0},"wc":{"gold":0,"silver":0,"bronze":0},"rank":32},{"id":14192462,"name_uk":"Швачка Таїсія","name_en":"Shvachka Taisiya","uc":{"gold":0,"silver":0,"bronze":0},"ec":{"gold":0,"silver":0,"bronze":0},"wc":{"gold":0,"silver":0,"bronze":0},"rank":32},{"id":14137089,"name_uk":"Шестакова Марія","name_en":"Shestakova Mariya","uc":{"gold":0,"silver":0,"bronze":0},"ec":{"gold":0,"silver":0,"bronze":0},"wc":{"gold":0,"silver":0,"bronze":0},"rank":32},{"id":14192489,"name_uk":"Ярошенко Софія","name_en":"Yaroshenko Sofiya","uc":{"gold":0,"silver":0,"bronze":0},"ec":{"gold":0,"silver":0,"bronze":0},"wc":{"gold":0,"silver":0,"bronze":0},"rank":32}]}